edge_pdf/__init__.py
edge_pdf/annot_add.py
edge_pdf/annot_logger.py
edge_pdf/annot_read.py
edge_pdf-1.0.0.dist-info/METADATA
edge_pdf-1.0.0.dist-info/WHEEL
edge_pdf-1.0.0.dist-info/entry_points.txt
edge_pdf-1.0.0.dist-info/top_level.txt
edge_pdf-1.0.0.dist-info/RECORD
